laminhub_rest/__init__.py
laminhub_rest/__main__.py
laminhub_rest/_ci.py
laminhub_rest/_clean_ci.py
laminhub_rest/connector.py
laminhub_rest/main.py
laminhub_rest/core/__init__.py
laminhub_rest/core/account/__init__.py
laminhub_rest/core/account/_create_account.py
laminhub_rest/core/account/_create_organization_account.py
laminhub_rest/core/account/_delete_account.py
laminhub_rest/core/account/_get_account_instances.py
laminhub_rest/core/account/_get_account_organizations.py
laminhub_rest/core/account/_update_account.py
laminhub_rest/core/collaborator/__init__.py
laminhub_rest/core/collaborator/_add_collaborator.py
laminhub_rest/core/instance/__init__.py
laminhub_rest/core/instance/_delete_instance.py
laminhub_rest/core/instance/_get_account_role_for_instance.py
laminhub_rest/core/instance/_get_instance_accounts.py
laminhub_rest/core/instance/_get_instance_by_id.py
laminhub_rest/core/instance/_get_instance_by_name.py
laminhub_rest/core/instance/_update_instance.py
laminhub_rest/orm/_account.py
laminhub_rest/orm/_account_instance.py
laminhub_rest/orm/_account_related_instances.py
laminhub_rest/orm/_account_related_organizations.py
laminhub_rest/orm/_avatar.py
laminhub_rest/orm/_cloud_run_instance.py
laminhub_rest/orm/_db_user.py
laminhub_rest/orm/_instance.py
laminhub_rest/orm/_instance_related_accounts.py
laminhub_rest/orm/_organization_user.py
laminhub_rest/orm/_storage.py
laminhub_rest/routers/__init__.py
laminhub_rest/routers/account.py
laminhub_rest/routers/ci.py
laminhub_rest/routers/cloud_run.py
laminhub_rest/routers/collaborator.py
laminhub_rest/routers/deployment.py
laminhub_rest/routers/dev.py
laminhub_rest/routers/instance.py
laminhub_rest/routers/organization.py
laminhub_rest/routers/utils.py
laminhub_rest/routers/vault.py
laminhub_rest/schema/__init__.py
laminhub_rest/schema/_core.py
laminhub_rest/schema/_timestamps.py
laminhub_rest/schema/_type.py
laminhub_rest/schema/_users.py
laminhub_rest/schema/_versions.py
laminhub_rest/schema/alembic.ini
laminhub_rest-0.14.11.dist-info/entry_points.txt
laminhub_rest-0.14.11.dist-info/WHEEL
laminhub_rest-0.14.11.dist-info/METADATA
laminhub_rest-0.14.11.dist-info/RECORD
