Metadata-Version: 2.1
Name: laminhub_rest
Version: 0.14.11
Summary: Rest API for the hub.
Author-email: Lamin Labs <laminlabs@gmail.com>
Requires-Dist: lamin_logger
Requires-Dist: supabase==1.0.3
Requires-Dist: pyjwt
Requires-Dist: pydantic[dotenv]
Requires-Dist: fastapi
Requires-Dist: uvicorn
Requires-Dist: sqlmodel
Requires-Dist: alembic
Requires-Dist: pytest_alembic==0.9.1
Requires-Dist: psycopg2-binary
Requires-Dist: lamin_vault==0.1.2
Requires-Dist: pre-commit ; extra == "dev"
Requires-Dist: nox ; extra == "dev"
Requires-Dist: faker ; extra == "dev"
Requires-Dist: pytest>=6.0 ; extra == "dev"
Requires-Dist: pytest-cov ; extra == "dev"
Requires-Dist: botocore ; extra == "dev"
Requires-Dist: lamindb_setup ; extra == "dev"
Requires-Dist: deepdiff ; extra == "dev"
Requires-Dist: pytest-xdist ; extra == "dev"
Requires-Dist: requests ; extra == "dev"
Project-URL: Home, https://github.com/laminlabs/laminhub-rest
Provides-Extra: dev
